{
  "string": [
    {
      "name": "module_desc",
      "value": "EQ_Master是一款专注于提升用户情商的实用APP，旨在通过科学的方法和丰富的工具，帮助用户在情感管理和人际交往方面取得显著进步。"
    },
    {
      "name": "EntryAbility_desc",
      "value": "EQ_Master是一款专注于提升用户情商的实用APP，旨在通过科学的方法和丰富的工具，帮助用户在情感管理和人际交往方面取得显著进步。"
    },
    {
      "name": "EntryAbility_label",
      "value": "EQ Master"
    },
    {
      "name": "internet_reason",
      "value": "You need to obtain your network permission to obtain network resource display data."
    },
    {
      "name": "network_reason",
      "value": "You need to obtain your network status information to determine whether the current device is connected to the network."
    },
    {
      "name": "location_reason",
      "value": "Need to get your location information to plan your route."
    },
    {
      "name": "background_task_reason",
      "value": "You need to obtain your background task permission for background AI broadcast."
    },
    {
      "name": "distributed_data_sync",
      "value": "Used for free flow of multiple devices."
    },
    {
      "name": "pull_up_load_text",
      "value": "Loading in..."
    },
    {
      "name": "network_exception",
      "value": "The network seems to have deserted"
    },
    {
      "name": "skip",
      "value": "Jump"
    },
    {
      "name": "tab_discover",
      "value": "Explore"
    },
    {
      "name": "tab_learning",
      "value": "Learning"
    },
    {
      "name": "tab_challenge",
      "value": "Challenge"
    },
    {
      "name": "tab_activity",
      "value": "Conference"
    },
    {
      "name": "tab_mine",
      "value": "Me"
    },
    {
      "name": "topic_title_family",
      "value": "HarmonyHeiTi-Medium"
    },
    {
      "name": "topic_title_family_sub",
      "value": "HarmonyHeiTi"
    },
    {
      "name": "splash_main_title",
      "value": "HarmonyOSWorld"
    },
    {
      "name": "splash_sub_title",
      "value": "Welcome to HarmonyOS Developer's world"
    },
    {
      "name": "splash_button_title",
      "value": "Start your learning journey"
    },
    {
      "name": "button_agree",
      "value": "Agree"
    },
    {
      "name": "button_cancel",
      "value": "Cancel"
    },
    {
      "name": "safe_desc1_str1",
      "value": "This application requires"
    },
    {
      "name": "safe_desc1_str2",
      "value": " Networking "
    },
    {
      "name": "safe_desc1_str3",
      "value": "Invoking"
    },
    {
      "name": "safe_desc1_str4",
      "value": " XX、XX "
    },
    {
      "name": "safe_desc1_str5",
      "value": "Permission, use XX information, and provide XX services. At the same time, in order to open up the physical experience, value-added services will be opened based on your \"agreement\". For more information on the processing of personal information, please refer to the"
    },
    {
      "name": "safe_desc1_str6",
      "value": " Statement of HMOS World and Privacy"
    },
    {
      "name": "safe_desc1_str7",
      "value": "、Permission usage description."
    },
    {
      "name": "safe_desc2",
      "value": "Please read the above statement carefully. If you click Agree, you agree to the XX user agreement and enable the value-added service function."
    },
    {
      "name": "welcome_to_use",
      "value": "Welcome to"
    },
    {
      "name": "service_desc",
      "value": "Read the latest Harmony news and technical articles"
    },
    {
      "name": "privacy_statement",
      "value": "Privacy Statement"
    },
    {
      "name": "PhoneFormAbility_desc",
      "value": "Hot Discover"
    },
    {
      "name": "PhoneFormAbility_label",
      "value": "HarmonyOS World"
    },
    {
      "name": "popular_findings",
      "value": "Popular Findings"
    },
    {
      "name": "home_page_text",
      "value": "Hello World"
    },
    {
      "name": "eq_master_text",
      "value": "Healthy Living"
    },
    {
      "name": "eq_master_introduce",
      "value": "Achieve high emotional intelligence."
    },
    {
      "name": "advertising_text_title",
      "value": "Skip %ds"
    },
    {
      "name": "dialog_text_title",
      "value": "Welcome To EQ_Master"
    },
    {
      "name": "dialog_text_privacy_content",
      "value": "我们充分尊重用户的隐私权,并按照法律要求和业界成熟的安全标准,为您的个人信息提供相应的安全保护措施。"
    },
    {
      "name": "dialog_text_privacy_statement",
      "value": "隐私协议保护声明"
    },
    {
      "name": "dialog_text_declaration_prompt",
      "value": "（以下简称为\"本声明\"）以便您了解我们如何搜集、使用、披露、保护、存储及传输您的个人数据。请您仔细阅读本声明。如您有任何疑问，请告知我们。"
    },
    {
      "name": "dialog_button_disagree",
      "value": "不同意"
    },
    {
      "name": "dialog_button_agree",
      "value": "同意"
    },
    {
      "name": "privacy_text_title",
      "value": "隐私政策"
    },
    {
      "name": "privacy_text_content",
      "value": "本应用尊重并保护所有使用服务用户的个人隐私权。为了给您提供更准确、更有个性化的服务，本应用会按照本隐私权政策的规定使用和披露您的个人信息。但本应用将以高度的勤勉、审慎义务对待这些信息。除本隐私权政策另有规定外，在未征得您事先许可的情况下，本应用不会将这些信息对外披露或向第三方提供。本应用会不时更新本隐私权政策。 您在同意本应用服务使用协议之时，即视为您已经同意本隐私权政策全部内容。本隐私权政策属于本应用服务使用协议不可分割的一部分。\n\n1. 适用范围\n\n(a) 在您使用本应用网络服务，或访问本应用平台网页时，本应用自动接收并记录的您的浏览器和计算机上的信息，包括但不限于您的IP地址、浏览器的类型、使用的语言、访问日期和时间、软硬件特征信息及您需求的网页记录等数据；\n\n您了解并同意，以下信息不适用本隐私权政策：\n\n(a) 本应用收集到的您在本应用发布的有关信息数据，包括但不限于参与活动、成交信息及评价详情；\n\n(b) 违反法律规定或违反本应用规则行为及本应用已对您采取的措施。\n\n2. 信息使用\n\n(a)本应用不会向任何无关第三方提供、出售、出租、分享或交易您的个人信息，除非事先得到您的许可，或该第三方和本应用（含本应用关联公司）单独或共同为您提供服务，且在该服务结束后，其将被禁止访问包括其以前能够访问的所有这些资料。\n\n(b) 本应用亦不允许任何第三方以任何手段收集、编辑、出售或者无偿传播您的个人信息。任何本应用平台用户如从事上述活动，一经发现，本应用有权立即终止与该用户的服务协议。\n\n3. 信息披露\n\n在如下情况下，本应用将依据您的个人意愿或法律的规定全部或部分的披露您的个人信息：\n\n(a) 经您事先同意，向第三方披露；\n\n(b)为提供您所要求的产品和服务，而必须和第三方分享您的个人信息；\n\n(c) 根据法律的有关规定，或者行政或司法机构的要求，向第三方或者行政、司法机构披露；\n\n(d) 如您出现违反中国有关法律、法规或者本应用服务协议或相关规则的情况，需要向第三方披露；\n\n(e) 如您是适格的知识产权投诉人并已提起投诉，应被投诉人要求，向被投诉人披露，以便双方处理可能的权利纠纷；\n\n(f) 在本应用平台上创建的某一交易中，如交易任何一方履行或部分履行了交易义务并提出信息披露请求的，本应用有权决定向该用户提供其交易对方的联络方式等必要信息，以促成交易的完成或纠纷的解决。\n\n(g) 其它本应用根据法律、法规或者网站政策认为合适的披露。\n\n4. 信息存储和交换\n\n本应用收集的有关您的信息和资料将保存在本应用及（或）其关联公司的服务器上，这些信息和资料可能传送至您所在国家、地区或本应用收集信息和资料所在地的境外并在境外被访问、存储和展示。\n\n5. Cookie的使用\n\n(a) 在您未拒绝接受cookies的情况下，本应用会在您的计算机上设定或取用cookies ，以便您能登录或使用依赖于cookies的本应用平台服务或功能。本应用使用cookies可为您提供更加周到的个性化服务，包括推广服务。\n\n(b) 您有权选择接受或拒绝接受cookies。您可以通过修改浏览器设置的方式拒绝接受cookies。但如果您选择拒绝接受cookies，则您可能无法登录或使用依赖于cookies的本应用网络服务或功能。\n\n(c) 通过本应用所设cookies所取得的有关信息，将适用本政策。\n\n6. 信息安全\n\n(a) 本应用帐号均有安全保护功能，请妥善保管您的用户名及密码信息。本应用将通过对用户密码进行加密等安全措施确保您的信息不丢失，不被滥用和变造。尽管有前述安全措施，但同时也请您注意在信息网络上不存在“完善的安全措施”。\n\n(b) 在使用本应用网络服务进行网上交易时，您不可避免的要向交易对方或潜在的交易对\n\n7.本隐私政策的更改\n\n(a)如果决定更改隐私政策，我们会在本政策中、本公司网站中以及我们认为适当的位置发布这些更改，以便您了解我们如何收集、使用您的个人信息，哪些人可以访问这些信息，以及在什么情况下我们会透露这些信息。\n\n(b)本公司保留随时修改本政策的权利，因此请经常查看。如对本政策作出重大更改，本公司会通过网站通知的形式告知。\n\n请您妥善保护自己的个人信息，仅在必要的情形下向他人提供。如您发现自己的个人信息泄密，尤其是本应用用户名及密码发生泄露，请您立即联络本应用客服，以便本应用采取相应措施。"
    },
    {
      "name": "privacy_back",
      "value": "返回"
    },
    {
      "name": "first_page_text1",
      "value": "每日分享"
    },
    {
      "name": "first_page_text2",
      "value": "这个模块每天分享情商提升的实用技巧和启发心灵的故事，帮助用户更好地管理情绪、沟通和人际关系。"
    },
    {
      "name": "second_page_text1",
      "value": "情商测试"
    },
    {
      "name": "second_page_text2",
      "value": "这个模块通过一系列情商测试题，帮助用户评估自身情商水平，并根据结果提供详细评分，助力个人成长。"
    },
    {
      "name": "third_page_text1",
      "value": "高情商AI助手"
    },
    {
      "name": "third_page_text2",
      "value": "这个模块提供高情商AI助手，帮助用户在生活中应对并解决需要情商智慧的沟通和应答难题。"
    },
    {
      "name": "login_page",
      "value": "Login page"
    },
    {
      "name": "login_more",
      "value": "Log in to your account to use more services"
    },
    {
      "name": "account",
      "value": "手机号"
    },
    {
      "name": "password",
      "value": "密码"
    },
    {
      "name": "login",
      "value": "登录"
    },
    {
      "name": "register_account",
      "value": "没有账号？注册一个新的用户"
    },
    {
      "name": "forgot_password",
      "value": "忘记密码"
    },
    {
      "name": "message_login",
      "value": "短信验证码登录"
    },
    {
      "name": "other_login_method",
      "value": "其他登录方式"
    },
    {
      "name": "my_love",
      "value": "My favorite"
    },
    {
      "name": "history_record",
      "value": "History"
    },
    {
      "name": "message",
      "value": "Message"
    },
    {
      "name": "shopping_cart",
      "value": "Shopping cart"
    },
    {
      "name": "my_goal",
      "value": "My goal"
    },
    {
      "name": "group",
      "value": "Group"
    },
    {
      "name": "favorites",
      "value": "Favorites"
    },
    {
      "name": "recycle_bin",
      "value": "Recycle Bin"
    },
    {
      "name": "main_page",
      "value": "Home"
    },
    {
      "name": "mine_page",
      "value": "Mine"
    },
    {
      "name": "main_page_rankings",
      "value": "Rankings"
    },
    {
      "name": "main_page_others",
      "value": "Xiamen Station, we'll see you."
    },
    {
      "name": "main_page_new",
      "value": "New product debut"
    },
    {
      "name": "main_Page_brand",
      "value": "Big name flash"
    },
    {
      "name": "main_page_more",
      "value": "More Big Names"
    },
    {
      "name": "main_page_found",
      "value": "Find good things"
    },
    {
      "name": "mine_title_name",
      "value": "Mr. Lee"
    },
    {
      "name": "mine_title_email",
      "value": "2000000@shenhua.cc"
    },
    {
      "name": "mine_list_news",
      "value": "Push Notifications"
    },
    {
      "name": "mine_list_data",
      "value": "Data Management"
    },
    {
      "name": "mine_list_menu",
      "value": "Menu Settings"
    },
    {
      "name": "mine_list_about",
      "value": "About"
    },
    {
      "name": "mine_list_storage",
      "value": "Clear Cache"
    },
    {
      "name": "mine_list_privacy",
      "value": "Privacy Agreement"
    },
    {
      "name": "mine_button",
      "value": "Logout"
    },
    {
      "name": "home_list",
      "value": "List"
    },
    {
      "name": "mine_toggle",
      "value": "switch"
    },
    {
      "name": "incomplete_toast",
      "value": "This function is not perfect, please look forward to it."
    },
    {
      "name": "please_input_account",
      "value": "Please input the account"
    },
    {
      "name": "please_input_password",
      "value": "Please input the password"
    },
    {
      "name": "open_my_love",
      "value": "Open my favorite"
    },
    {
      "name": "open_history_record",
      "value": "Open history"
    },
    {
      "name": "open_message",
      "value": "Open message"
    },
    {
      "name": "open_shopping_cart",
      "value": "Open shopping cart"
    },
    {
      "name": "open_my_goal",
      "value": "Open my goal"
    },
    {
      "name": "open_group",
      "value": "Open group"
    },
    {
      "name": "open_favorites",
      "value": "Open favorites"
    },
    {
      "name": "open_recycle_bin",
      "value": "Open Recycle Bin"
    },
    {
      "name": "open_rankings",
      "value": "Open rankings"
    },
    {
      "name": "open_new",
      "value": "Open new product debut"
    },
    {
      "name": "open_brand",
      "value": "Open big name flash"
    },
    {
      "name": "open_found",
      "value": "Open find good things"
    },
    {
      "name": "open_news",
      "value": "Push is on"
    },
    {
      "name": "close_news",
      "value": "Push is off"
    },
    {
      "name": "open_data",
      "value": "Open data management"
    },
    {
      "name": "open_menu",
      "value": "Open menu settings"
    },
    {
      "name": "open_about",
      "value": "Open about"
    },
    {
      "name": "clear_storage",
      "value": "Clear cache succeeded"
    },
    {
      "name": "check_privacy",
      "value": "Check privacy agreement"
    },
    {
      "name": "input_empty_tips",
      "value": "输入不能为空"
    },
    {
      "name": "message_login_prompt",
      "value": "Incorrect user name or password. Please try again."
    },
    {
      "name": "success_login_prompt",
      "value": "登录成功！"
    },
    {
      "name": "success_signup_prompt",
      "value": "注册成功！"
    },
    {
      "name": "message_user_name",
      "value": "请输入用户名"
    },
    {
      "name": "message_telephone_prompt",
      "value": "请输入手机号"
    },
    {
      "name": "message_password_prompt",
      "value": "密码不一致，请重试"
    },
    {
      "name": "message_application_prompt",
      "value": "Please restart the application registration."
    },
    {
      "name": "register_page",
      "value": "注册"
    },
    {
      "name": "register_name",
      "value": "用户名"
    },
    {
      "name": "register_telephone",
      "value": "手机号"
    },
    {
      "name": "register_password",
      "value": "密码"
    },
    {
      "name": "register_confirm_password",
      "value": "确认密码"
    },
    {
      "name": "register_face_checkbox",
      "value": "Facial recognition login"
    },
    {
      "name": "register_fingerprint_checkbox",
      "value": "Fingerprint identification login"
    },
    {
      "name": "register_button",
      "value": "注册"
    },
    {
      "name": "main_tab_home",
      "value": "Home"
    },
    {
      "name": "home_title",
      "value": "index"
    },
    {
      "name": "main_tab_mine",
      "value": "Mine"
    },
    {
      "name": "mine_title",
      "value": "Mine"
    },
    {
      "name": "my_favorite",
      "value": "My Favorite"
    },
    {
      "name": "main_top",
      "value": "Rankings"
    },
    {
      "name": "main_text_top",
      "value": "Xiamen Station, we'll see you."
    },
    {
      "name": "main_new",
      "value": "New product debut"
    },
    {
      "name": "main_brand",
      "value": "Big name flash"
    },
    {
      "name": "main_found",
      "value": "Find good things"
    },
    {
      "name": "main_text_new",
      "value": "Xiamen Station, we'll see you."
    },
    {
      "name": "main_text_found",
      "value": "Xiamen Station, we'll see you."
    },
    {
      "name": "main_text_brand",
      "value": "More Big Names"
    },
    {
      "name": "setting_list_news",
      "value": "Push notifications"
    },
    {
      "name": "setting_list_data",
      "value": "Data management"
    },
    {
      "name": "setting_list_menu",
      "value": "Menu settings"
    },
    {
      "name": "setting_list_about",
      "value": "Clear cache"
    },
    {
      "name": "setting_list_storage",
      "value": "Clear the cache"
    },
    {
      "name": "setting_list_privacy",
      "value": "Privacy agreement"
    },
    {
      "name": "setting_toggle",
      "value": "switch"
    },
    {
      "name": "setting_account_name",
      "value": "Mr. Lee"
    },
    {
      "name": "setting_account_email",
      "value": "2000000@shenhua.cc"
    },
    {
      "name": "setting_button",
      "value": "Logout"
    },
    {
      "name": "access_biometric_reason",
      "value": "Used for login verification using biometric recognition capabilities."
    },
    {
      "name": "privacy_window_reason",
      "value": "Used to prohibit screenshots in login page scenarios."
    },
    {
      "name": "pull_down_refresh_text",
      "value": "The drop-down refresh"
    },
    {
      "name": "release_refresh_text",
      "value": "Loosen the refresh"
    },
    {
      "name": "refreshing_text",
      "value": "Is refreshing"
    },
    {
      "name": "refresh_success_text",
      "value": "Refresh the success"
    },
    {
      "name": "refresh_fail_text",
      "value": "Refresh the failure"
    },
    {
      "name": "http_error_message",
      "value": "网络请求失败，请稍后再试！"
    },
    {
      "name": "page_none_msg",
      "value": "网络加载错误"
    },
    {
      "name": "prompt_message",
      "value": "No more data"
    },
    {
      "name": "dependency_reason",
      "value": "Used to initiate network data requests."
    },
    {
      "name": "news_title_image_height",
      "value": "16vp"
    },
    {
      "name": "news_title_image_width",
      "value": "40vp"
    },
    {
      "name": "list_image_weight",
      "value": "110vp"
    },
    {
      "name": "list_image_height",
      "value": "110vp"
    },
    {
      "name": "image_margin",
      "value": "12vp"
    },
    {
      "name": "location_desc",
      "value": "Allow the app to obtain the device's location information in the news homepage scenario"
    },
    {
      "name": "approximately_location_desc",
      "value": "Allow the app to obtain the device's approximate location information in the news homepage scenario"
    },
    {
      "name": "news_page_height",
      "value": "93.3%"
    },
    {
      "name": "news_List_width",
      "value": "100%"
    },
    {
      "name": "news_list_margin_bottom",
      "value": "12vp"
    },
    {
      "name": "location",
      "value": "Location"
    },
    {
      "name": "hotCity",
      "value": "Hot cities in China"
    },
    {
      "name": "news_title_row_height",
      "value": "20vp"
    },
    {
      "name": "news_title_row_margin_top",
      "value": "10vp"
    },
    {
      "name": "city_text_width",
      "value": "23%"
    },
    {
      "name": "city_padding_right",
      "value": "10%"
    },
    {
      "name": "news_content_height",
      "value": "14vp"
    },
    {
      "name": "news_content_margin",
      "value": "10vp"
    },
    {
      "name": "news_column_margin",
      "value": "12vp"
    },
    {
      "name": "news_row_padding",
      "value": "12vp"
    },
    {
      "name": "news_item_height",
      "value": "130vp"
    },
    {
      "name": "text_input_border",
      "value": "1.5"
    },
    {
      "name": "home_header_stack_width",
      "value": "95%"
    },
    {
      "name": "mock1",
      "value": "mockDataThree.json"
    },
    {
      "name": "mock2",
      "value": "mockDataFour.json"
    },
    {
      "name": "refresh",
      "value": "Refresh successful"
    },
    {
      "name": "search_text",
      "value": "search"
    },
    {
      "name": "get_location",
      "value": "Get location"
    },
    {
      "name": "tab_bar_option_zero",
      "value": "每日分享"
    },
    {
      "name": "tab_bar_option_one",
      "value": "AI助手"
    },
    {
      "name": "tab_bar_option_two",
      "value": "情商测验"
    },
    {
      "name": "tab_bar_option_three",
      "value": "个人中心"
    },
    {
      "name": "blank_view_text",
      "value": "No data available at the moment"
    },
    {
      "name": "tab_bar_type1",
      "value": "All"
    },
    {
      "name": "tab_bar_type2",
      "value": "Domestic"
    },
    {
      "name": "tab_bar_type3",
      "value": "International"
    },
    {
      "name": "tab_bar_type4",
      "value": "Entertainment"
    },
    {
      "name": "tab_bar_type5",
      "value": "Military"
    },
    {
      "name": "tab_bar_type6",
      "value": "Sports"
    },
    {
      "name": "tab_bar_type7",
      "value": "Science and technology"
    },
    {
      "name": "tab_bar_type8",
      "value": "Finance and Economics"
    },
    {
      "name": "question",
      "value": "考验情商的热门问题"
    },
    {
      "name": "tip",
      "value": "提升情商小技巧"
    },
    {
      "name": "story",
      "value": "情商趣味故事"
    },
    {
      "name": "recently",
      "value": "Recent Plays"
    },
    {
      "name": "photo",
      "value": "camera"
    },
    {
      "name": "more",
      "value": "more >"
    },
    {
      "name": "movie_classic",
      "value": "Selected Films"
    },
    {
      "name": "lately",
      "value": "latest"
    },
    {
      "name": "like",
      "value": "like"
    },
    {
      "name": "comment",
      "value": "comment"
    },
    {
      "name": "share",
      "value": "share"
    },
    {
      "name": "movie",
      "value": "movie"
    },
    {
      "name": "movie_description_1",
      "value": "@HarmonyOS Official website"
    },
    {
      "name": "movie_description_2",
      "value": "#HarmonyOS Huawei Developer Conference"
    },
    {
      "name": "TV",
      "value": "TV"
    },
    {
      "name": "game",
      "value": "Game"
    },
    {
      "name": "live",
      "value": "Live"
    },
    {
      "name": "entertainment",
      "value": "Entertainment"
    },
    {
      "name": "shared_desc",
      "value": "description"
    },
    {
      "name": "placeholder",
      "value": "搜索或输入网址"
    },
    {
      "name": "read_total_rank",
      "value": "查看完整榜单"
    },
    {
      "name": "follow",
      "value": "关注"
    },
    {
      "name": "found",
      "value": "发现"
    },
    {
      "name": "read_total",
      "value": "查看全部"
    },
    {
      "name": "follow_list_name_1",
      "value": "摄影视觉"
    },
    {
      "name": "follow_list_date_1",
      "value": "2小时前·发布了动态"
    },
    {
      "name": "follow_list_type_1",
      "value": "登山"
    },
    {
      "name": "follow_list_subtype_1",
      "value": "旅游"
    },
    {
      "name": "follow_list_content_1",
      "value": "在山顶，你会觉得山再巍峨，人也能把它征服，而此时的…"
    },
    {
      "name": "follow_list_name_2",
      "value": "大自然的风采"
    },
    {
      "name": "follow_list_date_2",
      "value": "11小时前·发布了动态"
    },
    {
      "name": "follow_list_name_3",
      "value": "山水"
    },
    {
      "name": "follow_list_date_3",
      "value": "3小时前·发布了动态"
    },
    {
      "name": "follow_list_name_4",
      "value": "最科技评测"
    },
    {
      "name": "follow_list_date_4",
      "value": "刚刚"
    },
    {
      "name": "follow_list_name_5",
      "value": "故宫画家"
    },
    {
      "name": "follow_list_name_6",
      "value": "国学展览"
    },
    {
      "name": "follow_list_date_6",
      "value": "8小时前·发布了动态"
    },
    {
      "name": "follow_list_name_7",
      "value": "自然社区"
    },
    {
      "name": "follow_list_name_8",
      "value": "摄影视效"
    },
    {
      "name": "follow_list_date_8",
      "value": "13小时前·发布了动态"
    },
    {
      "name": "follow_list_name_9",
      "value": "国学探究"
    },
    {
      "name": "follow_detail_name_1",
      "value": "全部关注"
    },
    {
      "name": "follow_detail_name_2",
      "value": "大自然的风采"
    },
    {
      "name": "follow_detail_name_3",
      "value": "科技评测"
    },
    {
      "name": "follow_detail_name_4",
      "value": "风景画家"
    },
    {
      "name": "follow_detail_name_5",
      "value": "自然社区"
    },
    {
      "name": "follow_detail_name_6",
      "value": "自然社区"
    },
    {
      "name": "follow_detail_content_1",
      "value": "摄影/10粉丝"
    },
    {
      "name": "follow_detail_content_2",
      "value": "摄影/5万粉丝"
    },
    {
      "name": "follow_detail_content_3",
      "value": "20万粉丝"
    },
    {
      "name": "follow_detail_content_4",
      "value": "快速评测"
    },
    {
      "name": "follow_detail_content_5",
      "value": "爱山爱水"
    },
    {
      "name": "follow_detail_content_6",
      "value": "国学认证"
    },
    {
      "name": "follow_detail_content_7",
      "value": "3万粉丝"
    },
    {
      "name": "follow_detail_content_8",
      "value": "2小时前发布了..."
    },
    {
      "name": "follow_title_content",
      "value": "的动态"
    },
    {
      "name": "today_hot_search",
      "value": "今日热搜"
    },
    {
      "name": "news_hot_search",
      "value": "要闻热搜"
    },
    {
      "name": "same_city_hot_search",
      "value": "同城热搜"
    },
    {
      "name": "entertainment_hot_search",
      "value": "娱乐热搜"
    },
    {
      "name": "food_hot_search",
      "value": "美食热搜"
    },
    {
      "name": "name_1",
      "value": "小鱼儿"
    },
    {
      "name": "name_2",
      "value": "熊猫大人"
    },
    {
      "name": "name_3",
      "value": "飞行日记"
    },
    {
      "name": "name_4",
      "value": "江湖旅客"
    },
    {
      "name": "name_5",
      "value": "摄影D叔"
    },
    {
      "name": "name_6",
      "value": "柯基可可"
    },
    {
      "name": "name_7",
      "value": "会飞的鱼儿"
    },
    {
      "name": "name_8",
      "value": "摄影学家王教授"
    },
    {
      "name": "name_9",
      "value": "雪中小镇"
    },
    {
      "name": "name_10",
      "value": "江湖游客"
    },
    {
      "name": "name_11",
      "value": "吕家寨子"
    },
    {
      "name": "author_type_1",
      "value": "环保领域作者"
    },
    {
      "name": "author_type_2",
      "value": "科技领域作者"
    },
    {
      "name": "author_type_3",
      "value": "旅行领域作者"
    },
    {
      "name": "author_type_4",
      "value": "风景摄影领域作者"
    },
    {
      "name": "content_1",
      "value": "亲近大海，领悟海，体会到了海的心声，海自然与你共鸣，无需可以强求，也无需费力搜寻，海，始终都会以潮声与你相亲，已其海色伴你舒适。亲近大海，领悟海，体会到了海的心声，海自然与你共鸣，无需可以强求，也无需费力搜寻，海，始终都会以潮声与你相亲，已其海色伴你舒适。"
    },
    {
      "name": "content_2",
      "value": "野生动物与宠物动物，可爱的动物人人都喜欢。野生动物与宠物动物，可爱的动物人人都喜欢。野生动物与宠物动物，可爱的动物人人都喜欢。野生动物与宠物动物，可爱的动物人人都喜欢。野生动物与宠物动物，可爱的动物人人都喜欢。野生动物与宠物动物，可爱的动物人人都喜欢。"
    },
    {
      "name": "content_3",
      "value": "君不见，黄河之水天上来，奔流到海不复回。君不见，高堂明镜悲白发，朝如青丝暮成雪。人生得意须尽欢，莫使金樽空对月。天生我材必有用，千金散尽还复来。烹羊宰牛且为乐，会须一饮三百杯。岑夫子，丹丘生，将进酒，杯莫停。与君歌一曲，请君为我倾耳听。钟鼓馔玉不足贵，但愿长醉不愿醒。古来圣贤皆寂寞，惟有饮者留其名。陈王昔时宴平乐，斗酒十千恣欢谑。主人何为言少钱，径须沽取对君酌。五花马，千金裘，呼儿将出换美酒，与尔同销万古愁。"
    },
    {
      "name": "content_4",
      "value": "群鸟，仿佛从大地的心窝飞起的音符。旋风似的从田野腾空而起。小鸟的头部两侧镶嵌着一双宝石般的小眼睛，嘴巴长长的，上面是它的小鼻子。群鸟，仿佛从大地的心窝飞起的音符。旋风似的从田野腾空而起。小鸟的头部两侧镶嵌着一双宝石般的小眼睛，嘴巴长长的，上面是它的小鼻子。"
    },
    {
      "name": "content_5",
      "value": "伫立于河流两岸的山峦，如同沉默无言的僧侣，眺望着远方。伫立于河流两岸的山峦，如同沉默无言的僧侣，眺望着远方。伫立于河流两岸的山峦，如同沉默无言的僧侣，眺望着远方。伫立于河流两岸的山峦，如同沉默无言的僧侣，眺望着远方。"
    },
    {
      "name": "content_6",
      "value": "九如山的山，山山相连，连绵起伏。山腰盘旋的那曲折险峻的实木栈道，如缕缕飘带缠绕在绿水青山之中，成为一道独特的亮丽风景；幽深的小谷之中，升腾着鬼神莫测的云雾。九如山的山，山山相连，连绵起伏。山腰盘旋的那曲折险峻的实木栈道，如缕缕飘带缠绕在绿水青山之中，成为一道独特的亮丽风景；幽深的小谷之中，升腾着鬼神莫测的云雾。"
    },
    {
      "name": "content_7",
      "value": "拍的很好啊！赞"
    },
    {
      "name": "content_8",
      "value": "滚滚长江东逝水，浪花淘尽英雄。"
    },
    {
      "name": "content_9",
      "value": "这组图片饱含了国风风格"
    },
    {
      "name": "content_10",
      "value": "会当凌绝顶！"
    },
    {
      "name": "content_11",
      "value": "拍的真好！爱了爱了！"
    },
    {
      "name": "content_12",
      "value": "千古江湖图一醉"
    },
    {
      "name": "content_13",
      "value": "好看，期待更新"
    },
    {
      "name": "content_14",
      "value": "规范野生动植物管理"
    },
    {
      "name": "content_15",
      "value": "人类建筑史上的奇迹"
    },
    {
      "name": "content_16",
      "value": "雾绕青山枝叶绿"
    },
    {
      "name": "content_17",
      "value": "舞者们台下十年练习之路"
    },
    {
      "name": "content_18",
      "value": "揭秘宇宙的奥秘"
    },
    {
      "name": "content_19",
      "value": "欧洲建筑的历史责任在对欧洲..."
    },
    {
      "name": "content_20",
      "value": "世界十大神奇建筑指的是建筑造型..."
    },
    {
      "name": "content_21",
      "value": "小小世界的生存智慧是非常..."
    },
    {
      "name": "content_22",
      "value": "艺术如同一首悠扬的乐曲"
    },
    {
      "name": "content_23",
      "value": "浩瀚宇宙有边际吗"
    },
    {
      "name": "content_24",
      "value": "人的精神世界的总和"
    },
    {
      "name": "content_25",
      "value": "夏天的气息扑面而来"
    },
    {
      "name": "content_26",
      "value": "这里的花开了"
    },
    {
      "name": "content_27",
      "value": "旅行是种什么体验"
    },
    {
      "name": "content_28",
      "value": "吉他有许多不同的音色"
    },
    {
      "name": "content_29",
      "value": "轻轻地拂过我的耳畔"
    },
    {
      "name": "content_30",
      "value": "静下来做事是难得的品质"
    },
    {
      "name": "content_31",
      "value": "红彤彤的苹果像小灯笼"
    },
    {
      "name": "content_32",
      "value": "带你去吃健康的蔬菜"
    },
    {
      "name": "content_33",
      "value": "儿时香甜的味道"
    },
    {
      "name": "time_position_1",
      "value": "10分钟前·来自上海"
    },
    {
      "name": "time_position_2",
      "value": "10-23·来自上海"
    },
    {
      "name": "time_position_3",
      "value": "10-22·来自上海"
    },
    {
      "name": "time_position_4",
      "value": "10-21·来自上海"
    },
    {
      "name": "time_position_5",
      "value": "10-19·来自上海"
    },
    {
      "name": "time_position_6",
      "value": "10-13·来自上海"
    },
    {
      "name": "sub_content_1",
      "value": "长江：对了//@森林：是佳能拍出的效果啊，太赞了"
    },
    {
      "name": "title_1",
      "value": "野生动物保护"
    },
    {
      "name": "title_2",
      "value": "世界有名建筑"
    },
    {
      "name": "title_3",
      "value": "茶叶的神奇功效"
    },
    {
      "name": "title_4",
      "value": "舞动者们"
    },
    {
      "name": "title_5",
      "value": "宇宙最遥远的样子"
    },
    {
      "name": "title_6",
      "value": "建筑人文"
    },
    {
      "name": "title_7",
      "value": "世界十大神奇建筑"
    },
    {
      "name": "title_8",
      "value": "生命之谜语"
    },
    {
      "name": "title_9",
      "value": "艺术之美"
    },
    {
      "name": "title_10",
      "value": "太空高清图片"
    },
    {
      "name": "title_11",
      "value": "心灵的修行"
    },
    {
      "name": "title_12",
      "value": "夏天来了"
    },
    {
      "name": "title_13",
      "value": "新的打卡景点"
    },
    {
      "name": "title_14",
      "value": "带宠物去旅行"
    },
    {
      "name": "title_15",
      "value": "吉他之声"
    },
    {
      "name": "title_16",
      "value": "聆听美妙的声音"
    },
    {
      "name": "title_17",
      "value": "安静的工作"
    },
    {
      "name": "title_18",
      "value": "超市的果子"
    },
    {
      "name": "title_19",
      "value": "蔬菜种植"
    },
    {
      "name": "title_20",
      "value": "儿时的味道"
    },
    {
      "name": "rank_title",
      "value": "热搜榜单"
    },
    {
      "name": "ran_sub_title",
      "value": "最新最热大事件都在这"
    },
    {
      "name": "detail_write_comment",
      "value": "写评论"
    },
    {
      "name": "comment_list_title",
      "value": "评论"
    },
    {
      "name": "card_detail_title",
      "value": "详情页"
    },
    {
      "name": "blog_follow",
      "value": "关注"
    },
    {
      "name": "author_type_name",
      "value": "楼主"
    },
    {
      "name": "replay",
      "value": "回复"
    },
    {
      "name": "read_all_replay",
      "value": "查看全部回复"
    },
    {
      "name": "test_sm",
      "value": "sm"
    },
    {
      "name": "test_md",
      "value": "md"
    },
    {
      "name": "test_lg",
      "value": "lg"
    },
    {
      "name": "test_aaa",
      "value": "11fp"
    },
    {
      "name": "Message",
      "value": "消息"
    },
    {
      "name": "Contacts",
      "value": "通讯录"
    },
    {
      "name": "SocialCircle",
      "value": "朋友圈"
    },
    {
      "name": "Me",
      "value": "我的"
    },
    {
      "name": "news",
      "value": "最新动态"
    },
    {
      "name": "card",
      "value": "名片夹"
    },
    {
      "name": "Alan",
      "value": "阿兰"
    },
    {
      "name": "AQin",
      "value": "AQin"
    },
    {
      "name": "CaiLan",
      "value": "菜篮"
    },
    {
      "name": "Deng",
      "value": "邓双双"
    },
    {
      "name": "excel",
      "value": "excel教程"
    },
    {
      "name": "FanYi",
      "value": "翻译"
    },
    {
      "name": "FenFen",
      "value": "芬芬"
    },
    {
      "name": "ge",
      "value": "哥白尼"
    },
    {
      "name": "LiX",
      "value": "李小二"
    },
    {
      "name": "Ma",
      "value": "马老师"
    },
    {
      "name": "milk",
      "value": "芬芬邀请你喝奶茶啦"
    },
    {
      "name": "Speed",
      "value": "请你喝奶茶，快点单吧！！速度速度，就差你了"
    },
    {
      "name": "happy",
      "value": "哈哈，今天有什么喜事说来听听"
    },
    {
      "name": "plan",
      "value": "市场部2023年新产品宣传规划"
    },
    {
      "name": "jack",
      "value": "这是明天会议的资料，请发给Jack，让他确认"
    },
    {
      "name": "ok",
      "value": "好的，收到"
    },
    {
      "name": "okay",
      "value": "好的，我明天过去"
    },
    {
      "name": "yesterday",
      "value": "昨天"
    },
    {
      "name": "document",
      "value": "文档"
    },
    {
      "name": "search",
      "value": "搜索..."
    }
  ]
}