{
  "HVIGOR_OHOS_PLUGIN": {
    "MODULES": [
      {
        "MODULE_NAME": "f7a42fe7211f98ac7a60a285ac3a9e87",
        "API_TYPE": "stageMode",
        "INCREMENTAL_TASKS": {
          "COMPILE_ARKTS": true
        }
      }
    ],
    "BUILD_MODE": "debug"
  },
  "HVIGOR": {
    "IS_INCREMENTAL": true,
    "IS_DAEMON": true,
    "IS_PARALLEL": true,
    "IS_HVIGORFILE_TYPE_CHECK": false,
    "TASK_TIME": {
      "f7a42fe7211f98ac7a60a285ac3a9e87": {
        "ConfigureCmake": 296100,
        "PreCheckSyscap": 304200,
        "ProcessIntegratedHsp": 2957400,
        "BuildNativeWithCmake": 264600,
        "SyscapTransform": 3643700,
        "BuildNativeWithNinja": 990000,
        "BuildJS": 5193800,
        "CompileArkTS": 2403402000,
        "PackageHap": 1914131300,
        "SignHap": 1285500,
        "assembleHap": 202300
      }
    },
    "TOTAL_TIME": 4735426400,
    "BUILD_ID": "202501060256593390"
  }
}